{
  "projects": [
    {
      "id": "73de",
      "name": "New project",
      "description": "Opisanie",
      "taskCount": 0,
      "status": "To Do",
      "createdAt": "2025-03-06"
    },
    {
      "id": "f38b",
      "name": "New project",
      "description": "dfdf",
      "taskCount": 0,
      "status": "To Do",
      "createdAt": "2025-03-06"
    },
    {
      "id": "bbe9",
      "name": "new York",
      "description": "",
      "taskCount": 0,
      "status": "To Do",
      "createdAt": "2025-03-06"
    },
    {
      "id": "d72a",
      "name": "sdfsdf",
      "description": "",
      "taskCount": 0,
      "status": "To Do",
      "createdAt": "2025-03-06"
    },
    {
      "id": "a36a",
      "name": "Новый проект 1",
      "description": "опитсание 1",
      "taskCount": 0,
      "status": "To Do",
      "createdAt": "2025-03-06"
    },
    {
      "id": "d7df",
      "name": "sdfdsf",
      "description": "sdfsdf",
      "taskCount": 0,
      "status": "To Do",
      "createdAt": "2025-03-06"
    },
    {
      "id": "182e",
      "name": "xcgdfg",
      "description": "dfgdfg",
      "taskCount": 2,
      "status": "To Do",
      "createdAt": "2025-03-06"
    },
    {
      "id": "6861",
      "name": "sdfsdf",
      "description": "",
      "taskCount": 0,
      "status": "To Do",
      "createdAt": "2025-03-06"
    },
    {
      "id": "6e45",
      "name": "NAMBAONE 11",
      "description": "sdfsdfsdfsdgf",
      "taskCount": 0,
      "status": "Done",
      "createdAt": "2025-03-06"
    },
    {
      "id": "b33d",
      "name": "dsfgdfgdf",
      "description": "dfgdfg",
      "taskCount": 0,
      "status": "To Do",
      "createdAt": "2025-03-06"
    },
    {
      "id": "00d3",
      "name": "dfgdf",
      "description": "dfgdfg",
      "taskCount": 13,
      "status": "To Do",
      "createdAt": "2025-03-06"
    },
    {
      "id": "4533",
      "name": "ываываыва",
      "description": "",
      "taskCount": 0,
      "status": "To Do",
      "createdAt": "2025-03-06"
    },
    {
      "id": "c9bc",
      "name": "фывыфвфыв",
      "description": "",
      "taskCount": 0,
      "status": "To Do",
      "createdAt": "2025-03-06"
    }
  ],
  "tasks": [
    {
      "id": "1741276171233",
      "title": "dfgdfg",
      "assignee": "Марія",
      "status": "To Do",
      "dueDate": "23342-04-23",
      "projectId": "182e"
    },
    {
      "id": "1741276971391",
      "title": "ываыв",
      "assignee": "Іван",
      "status": "To Do",
      "dueDate": "12222-02-21",
      "projectId": "182e"
    },
    {
      "id": "1741278140341",
      "title": "sdfgsdf",
      "assignee": "Олександр",
      "status": "To Do",
      "dueDate": "2025-03-06",
      "projectId": "00d3"
    },
    {
      "id": 1741282038774,
      "title": "sdfd",
      "assignee": "Марія",
      "status": "To Do",
      "dueDate": "2026-03-12",
      "projectId": "00d3"
    },
    {
      "title": "sdfsdf",
      "assignee": "Олександр",
      "status": "To Do",
      "dueDate": "2222-12-12",
      "projectId": "00d3",
      "id": 1741292167551
    },
    {
      "title": "dfgdgdf",
      "assignee": "Олександр",
      "status": "To Do",
      "dueDate": "2025-03-06",
      "projectId": "00d3",
      "id": 1741292363462
    },
    {
      "title": "ываыва",
      "assignee": "Марія",
      "status": "To Do",
      "dueDate": "2025-03-06",
      "projectId": "00d3",
      "id": 1741292921479
    },
    {
      "title": "sdfdf",
      "assignee": "Олександр",
      "status": "To Do",
      "dueDate": "2025-03-06",
      "projectId": "00d3",
      "id": 1741293610700
    },
    {
      "title": "ываыва",
      "assignee": "Марія",
      "status": "To Do",
      "dueDate": "2025-03-06",
      "projectId": "00d3",
      "id": 1741293815754
    },
    {
      "title": "dfgdf",
      "assignee": "Марія",
      "status": "To Do",
      "dueDate": "2025-03-06",
      "projectId": "00d3",
      "id": 1741293883692
    },
    {
      "title": "sdfs",
      "assignee": "Марія",
      "status": "To Do",
      "dueDate": "2025-03-06",
      "projectId": "00d3",
      "id": 1741293996934
    },
    {
      "title": "sdfsd",
      "assignee": "Марія",
      "status": "To Do",
      "dueDate": "2025-04-05",
      "projectId": "00d3",
      "id": 1741294063060
    },
    {
      "title": "dfgdf",
      "assignee": "Марія",
      "status": "To Do",
      "dueDate": "2025-03-06",
      "projectId": "00d3",
      "id": 1741294127927
    },
    {
      "title": "sdfsdf",
      "assignee": "Марія",
      "status": "To Do",
      "dueDate": "2025-03-06",
      "projectId": "00d3",
      "id": 1741294140684
    },
    {
      "title": "dfgfd",
      "assignee": "Олександр",
      "status": "To Do",
      "dueDate": "2025-03-06",
      "projectId": "00d3",
      "id": 1741294381440
    }
  ]
}